ltcli/__init__.py
ltcli/__version__.py
ltcli/ask_util.py
ltcli/center.py
ltcli/cli.py
ltcli/cli_main.py
ltcli/cluster.py
ltcli/cluster_util.py
ltcli/color.py
ltcli/conf.py
ltcli/config.py
ltcli/deploy_util.py
ltcli/editor.py
ltcli/exceptions.py
ltcli/log.py
ltcli/message.py
ltcli/net.py
ltcli/parser.py
ltcli/prompt.py
ltcli/rediscli.py
ltcli/rediscli_util.py
ltcli/string.json
ltcli/thriftserver.py
ltcli/utils.py
ltcli/redistrib2/__init__.py
ltcli/redistrib2/clusternode.py
ltcli/redistrib2/command.py
ltcli/redistrib2/connection.py
ltcli/redistrib2/console.py
ltcli/redistrib2/custom_node.py
ltcli/redistrib2/custom_reshard.py
ltcli/redistrib2/custom_trib.py
ltcli/redistrib2/custom_util.py
ltcli/redistrib2/exceptions.py
ltcli-1.1.11.dist-info/LICENSE
ltcli-1.1.11.dist-info/METADATA
ltcli-1.1.11.dist-info/WHEEL
ltcli-1.1.11.dist-info/entry_points.txt
ltcli-1.1.11.dist-info/top_level.txt
ltcli-1.1.11.dist-info/RECORD
