Metadata-Version: 2.1
Name: ltcli
Version: 1.1.11
Summary: Command line tool for LightningDB
Home-page: https://lightningdb.io/
Author: LightningDB
Author-email: lightningdb@sktelecom.com
License: UNKNOWN
Platform: UNKNOWN
Classifier: Programming Language :: Python
Classifier: Programming Language :: Python :: 2
Classifier: Programming Language :: Python :: 2.7
Classifier: Programming Language :: Python :: 3
Classifier: Programming Language :: Python :: 3.5
Classifier: Programming Language :: Python :: 3.6
Classifier: Programming Language :: Python :: 3.7
Requires-Python: >=2.7, !=3.0.*, !=3.1.*, !=3.2.*, !=3.3.*, !=3.4.*
Requires-Dist: ask (==0.0.8)
Requires-Dist: prompt-toolkit (<=2.0.10,>=2.0.7)
Requires-Dist: Pygments (<=2.5.2,>=2.3.0)
Requires-Dist: logbook (<1.6.0,>=1.5.2)
Requires-Dist: paramiko (<=2.7.1,>=2.5.0)
Requires-Dist: redis-py-cluster (<=2.0.0,>=1.3.6)
Requires-Dist: terminaltables (==3.1.0)
Requires-Dist: retrying (==1.3.3)
Requires-Dist: requests (<2.23.0,>=2.22.0)
Requires-Dist: hiredis (<1.1.0,>=1.0.0)
Requires-Dist: Click (<=7.0,>=6.7)
Requires-Dist: six (<=1.13.0,>=1.11.0)
Requires-Dist: Werkzeug (>=0.14.1)
Requires-Dist: fire (<=0.2.1,>=0.1.3)
Requires-Dist: PyYAML (<=5.2.0,>=5.1.2)
Requires-Dist: redis (<3.1.0,>=3.0.0)
Requires-Dist: termcolor (==1.1.0)
Requires-Dist: chardet (<3.1.0,>=3.0.2)
Requires-Dist: idna (<2.9,>=2.5)
Requires-Dist: urllib3 (!=1.25.0,!=1.25.1,<1.26,>=1.21.1)
Requires-Dist: certifi (<=2019.11.28,>=2017.4.17)
Requires-Dist: wcwidth (==0.1.7)
Requires-Dist: pycparser (==2.19)
Requires-Dist: cffi (!=1.11.3,<=1.13.2,>=1.8)
Requires-Dist: PyNaCl (<=1.3.0,>=1.0.1)
Requires-Dist: cryptography (<=2.8,>=2.5)
Requires-Dist: bcrypt (<=3.1.7,>=3.1.3)
Requires-Dist: enum34 (==1.1.6)
